fiveclocks.v
// Design
// D flip-flop
module fiveclocks (clk,b,reset,t,tt,ttt,tttt,ttttt,m);
  input      clk;
  input      b;
  input		 reset;
  output     t,tt,ttt,tttt,ttttt,m;

  reg        the,thethe,thethethe,thethethethe,thethethethethe;
  reg 		 memory;

  assign t = the;
  assign tt = thethe;
  assign ttt = thethethe;
  assign tttt = thethethethe;
  assign ttttt = thethethethethe;
  assign m = memory;
  
  always @ ( posedge clk )
  begin
    if ( reset ) begin
      // Asynchronous reset when reset goes high
      the = 1;
      thethe = 0;
      thethethe = 0;
      thethethethe = 0;
      thethethethethe = 0;
      memory = 0;
    end else begin
      // Assign D to Q on positive clock edge
      the = ~the;
      if ( the ) begin
      	 thethe = ~ thethe; 
        if ( thethe ) begin
          	thethethe = ~thethethe;
          if ( thethethe ) begin
            thethethethe = ~ thethethethe;
            if ( thethethethe ) begin
            thethethethethe = ~ thethethethethe;
              if ( thethethethethe ) begin
                	memory = b;
              end else begin
                	memory = memory;
              end
          end else begin
            thethethethethe = thethethethethe;
          end
          end else begin
            thethethethe = thethethethe;
          end
        end else begin
          thethethe = thethethe;
        end
      end else begin
         thethe = thethe;
      end
    end
  end
endmodule

five_clocks_tb.v
// Verilog test bench for example_3_1
`timescale 1ns/100ps
`include "fiveclocks.v"

module five_clocks_tb;

  reg clk;
  wire to_clock;
  reg reset;
  reg b;
  wire m;
  wire t, tt, ttt, tttt, ttttt;
  // Instantiate design under test
  fiveclocks FC(.clk(clk),.b( b ),.reset(reset),.t(t),.tt(tt),.ttt(ttt),.tttt(tttt),.ttttt(ttttt),.m(m));

   initial begin
      $dumpfile("fiveclocks.vcd");
      $dumpvars(0, five_clocks_tb);
      b = 0;
      clk = 0;
      reset = 1; 
      display;
      clk = 1;
      
      display;
      clk = 0;
      display;
      clk = 1;
      display;
      reset = 0;
       display;    
clk =  1 ; display;    
clk =  1 ; display;    
clk =  0 ; display;    
clk =  1 ; display;    
clk =  1 ; display;    
clk =  0 ; display;    
clk =  0 ; display;    
clk =  0 ; display;    
clk =  1 ; display;    
clk =  1 ; display;    
clk =  1 ; display;    
clk =  0 ; display;    
clk =  1 ; display;    
clk =  1 ; display;    
clk =  1 ; display;    
clk =  0 ; display;    
clk =  1 ; display;    
clk =  1 ; display;    
clk =  1 ; display;    
clk =  1 ; display;    
clk =  1 ; display;    
clk =  0 ; display;    
clk =  0 ; display;    
clk =  1 ; display;    
clk =  1 ; display;    
clk =  1 ; display;    
clk =  0 ; display;    
clk =  0 ; display;    
clk =  0 ; display;    
clk =  0 ; display;    
clk =  1 ; display;    
clk =  0 ; display;    
clk =  0 ; display;    
clk =  0 ; display;    
clk =  1 ; display;    
clk =  0 ; display;    
clk =  0 ; display;    
clk =  1 ; display;    
clk =  1 ; display;    
clk =  0 ; display;    
clk =  0 ; display;    
clk =  0 ; display;    
clk =  1 ; display;    
clk =  1 ; display;    
clk =  1 ; display;    
clk =  0 ; display;    
clk =  1 ; display;    
clk =  0 ; display;    
clk =  1 ; display;    
clk =  0 ; display;    
clk =  1 ; display;    
clk =  0 ; display;    
clk =  0 ; display;    
clk =  0 ; display;    
clk =  1 ; display;    
clk =  1 ; display;    
clk =  0 ; display;    
clk =  1 ; display;    
clk =  0 ; display;    
clk =  0 ; display;    
clk =  1 ; display;    
clk =  1 ; display;    
clk =  0 ; display;    
clk =  1 ; display;    
clk =  0 ; display;    
clk =  1 ; display;    
clk =  0 ; display;    
clk =  0 ; display;    
clk =  0 ; display;    
clk =  1 ; display;    
clk =  0 ; display;    
clk =  0 ; display;    
clk =  1 ; display;    
clk =  0 ; display;    
clk =  0 ; display;    
clk =  0 ; display;    
clk =  0 ; display;    
clk =  1 ; display;    
clk =  0 ; display;    
clk =  0 ; display;    
clk =  0 ; display;    
clk =  1 ; display;    
clk =  0 ; display;    
clk =  1 ; display;    
clk =  0 ; display;    
clk =  0 ; display;    
clk =  0 ; display;    
clk =  1 ; display;    
clk =  1 ; display;    
clk =  1 ; display;    
clk =  0 ; display;    
clk =  1 ; display;    
clk =  1 ; display;    
clk =  0 ; display;    
clk =  0 ; display;    
clk =  1 ; display;    
clk =  0 ; display;    
clk =  0 ; display;    
clk =  1 ; display;    
clk =  1 ; display;    
clk =  1 ; display;    
clk =  1 ; display;    
clk =  0 ; display;    
clk =  1 ; display;    
clk =  1 ; display;    
clk =  1 ; display;    
clk =  0 ; display;    
clk =  0 ; display;    
clk =  1 ; display;    
clk =  1 ; display;    
clk =  1 ; display;    
clk =  0 ; display;    
clk =  0 ; display;    
clk =  1 ; display;    
clk =  0 ; display;    
clk =  1 ; display;    
clk =  0 ; display;    
clk =  1 ; display;    
clk =  0 ; display;    
clk =  0 ; display;    
clk =  0 ; display;    
clk =  0 ; display;    
clk =  1 ; display;    
clk =  0 ; display;    
clk =  0 ; display;    
clk =  1 ; display;    
clk =  0 ; display;    
clk =  0 ; display;    
clk =  1 ; display;    
clk =  0 ; display;    
clk =  0 ; display;    
clk =  1 ; display;    
clk =  1 ; display;    
clk =  0 ; display;    
clk =  1 ; display;    
clk =  0 ; display;    
clk =  1 ; display;    
clk =  0 ; display;    
clk =  0 ; display;    
clk =  1 ; display;    
clk =  1 ; display;    
clk =  1 ; display;    
clk =  0 ; display;    
clk =  1 ; display;    
clk =  1 ; display;    
clk =  0 ; display;    
clk =  0 ; display;    
clk =  1 ; display;    
clk =  0 ; display;    
clk =  0 ; display;    
clk =  1 ; display;    
clk =  1 ; display;    
clk =  0 ; display;    
clk =  1 ; display;    
clk =  1 ; display;    
clk =  1 ; display;    
clk =  1 ; display;    
clk =  1 ; display;    
clk =  0 ; display;    
clk =  1 ; display;    
clk =  1 ; display;    
clk =  1 ; display;    
clk =  0 ; display;    
clk =  1 ; display;    
clk =  1 ; display;    
clk =  1 ; display;    
clk =  0 ; display;    
clk =  0 ; display;    
clk =  1 ; display;    
clk =  1 ; display;    
clk =  1 ; display;    
clk =  0 ; display;    
clk =  1 ; display;    
clk =  1 ; display;    
clk =  0 ; display;    
clk =  0 ; display;    
clk =  1 ; display;    
clk =  0 ; display;    
clk =  1 ; display;    
clk =  1 ; display;    
clk =  1 ; display;    
clk =  1 ; display;    
clk =  1 ; display;    
clk =  0 ; display;    
clk =  0 ; display;    
clk =  0 ; display;    
clk =  0 ; display;    
clk =  1 ; display;    
clk =  0 ; display;    
clk =  1 ; display;    
clk =  0 ; display;    
clk =  0 ; display;    
clk =  1 ; display;    
clk =  1 ; display;    
clk =  1 ; display;    
clk =  1 ; display;    
clk =  1 ; display;    
clk =  1 ; display;    
clk =  1 ; display;    
clk =  1 ; display;    
clk =  0 ; display;    
clk =  0 ; display;    
clk =  0 ; display;    
clk =  0 ; display;    
clk =  1 ; display;    
clk =  1 ; display;    
clk =  0 ; display;    
clk =  1 ; display;    
clk =  1 ; display;    
clk =  0 ; display;    
clk =  1 ; display;    
clk =  1 ; display;    
clk =  1 ; display;    
clk =  0 ; display;    
clk =  1 ; display;    
clk =  0 ; display;    
clk =  0 ; display;    
clk =  0 ; display;    
clk =  0 ; display;    
clk =  1 ; display;    
clk =  1 ; display;    
clk =  0 ; display;    
clk =  0 ; display;    
clk =  1 ; display;    
clk =  1 ; display;    
clk =  0 ; display;    
clk =  1 ; display;    
clk =  1 ; display;    
clk =  1 ; display;    
clk =  0 ; display;    
clk =  1 ; display;    
clk =  1 ; display;    
clk =  1 ; display;    
clk =  0 ; display;    
clk =  1 ; display;    
clk =  1 ; display;    
clk =  1 ; display;    
clk =  1 ; display;    
clk =  0 ; display;    
clk =  0 ; display;    
clk =  0 ; display;    
clk =  0 ; display;    
clk =  0 ; display;    
clk =  0 ; display;    
clk =  1 ; display;    
clk =  1 ; display;    
clk =  1 ; display;    
clk =  0 ; display;    
clk =  0 ; display;    
clk =  1 ; display;    
clk =  0 ; display;    
clk =  0 ; display;    
clk =  1 ; display;    
clk =  0 ; display;    
clk =  0 ; display;    
clk =  1 ; display;    
clk =  0 ; display;    
clk =  0 ; display;    
clk =  1 ; display;    
clk =  0 ; display;    
clk =  1 ; display;    
clk =  1 ; display;    
clk =  1 ; display;    
clk =  0 ; display;    
clk =  1 ; display;    
clk =  1 ; display;    
clk =  1 ; display;    
clk =  0 ; display;    
clk =  0 ; display;    
clk =  1 ; display;    
clk =  1 ; display;    
clk =  1 ; display;    
clk =  0 ; display;    
clk =  1 ; display;    
clk =  0 ; display;    
clk =  0 ; display;    
clk =  0 ; display;    
clk =  0 ; display;    
clk =  0 ; display;    
clk =  1 ; display;    
clk =  1 ; display;    
clk =  0 ; display;    
clk =  0 ; display;    
clk =  1 ; display;    
clk =  0 ; display;    
clk =  1 ; display;    
clk =  1 ; display;    
clk =  1 ; display;    
clk =  1 ; display;    
clk =  1 ; display;    
clk =  0 ; display;    
clk =  1 ; display;    
clk =  1 ; display;    
clk =  0 ; display;    
clk =  1 ; display;    
clk =  1 ; display;    
clk =  1 ; display;    
clk =  1 ; display;    
clk =  1 ; display;    
clk =  0 ; display;    
clk =  0 ; display;    
clk =  0 ; display;    
clk =  0 ; display;    
clk =  0 ; display;    
clk =  1 ; display;    
clk =  1 ; display;    
clk =  0 ; display;    
clk =  0 ; display;    
clk =  0 ; display;    
clk =  0 ; display;    
clk =  0 ; display;    
clk =  0 ; display;    
clk =  1 ; display;    
clk =  0 ; display;    
clk =  1 ; display;    
clk =  1 ; display;    
clk =  1 ; display;    
clk =  1 ; display;    
clk =  1 ; display;    
clk =  1 ; display;    
clk =  0 ; display;    
clk =  1 ; display;    
clk =  0 ; display;    
clk =  1 ; display;    
clk =  0 ; display;    
clk =  0 ; display;    
clk =  0 ; display;    
clk =  1 ; display;    
clk =  1 ; display;    
clk =  0 ; display;    
clk =  1 ; display;    
clk =  0 ; display;    
clk =  0 ; display;    
clk =  0 ; display;    
clk =  1 ; display;    
clk =  1 ; display;    
clk =  1 ; display;    
clk =  1 ; display;    
clk =  1 ; display;    
clk =  0 ; display;    
clk =  1 ; display;    
clk =  1 ; display;    
clk =  0 ; display;    
clk =  1 ; display;    
clk =  0 ; display;    
clk =  0 ; display;    
clk =  1 ; display;    
clk =  0 ; display;    
clk =  1 ; display;    
clk =  0 ; display;    
clk =  0 ; display;    
clk =  1 ; display;    
clk =  0 ; display;    
clk =  1 ; display;    
clk =  1 ; display;    
clk =  0 ; display;    
clk =  0 ; display;    
clk =  1 ; display;    
clk =  0 ; display;    
clk =  0 ; display;    
clk =  0 ; display;    
clk =  1 ; display;    
clk =  0 ; display;    
clk =  0 ; display;    
clk =  1 ; display;    
clk =  1 ; display;    
clk =  1 ; display;    
clk =  1 ; display;    
clk =  1 ; display;    
clk =  1 ; display;    
clk =  0 ; display;    
clk =  0 ; display;    
clk =  0 ; display;    
clk =  1 ; display;    
clk =  0 ; display;    
clk =  0 ; display;    
clk =  0 ; display;    
clk =  1 ; display;    
clk =  1 ; display;    
clk =  1 ; display;    
clk =  0 ; display;    
clk =  0 ; display;    
clk =  1 ; display;    
clk =  1 ; display;    
clk =  1 ; display;    
clk =  0 ; display;    
clk =  1 ; display;    
clk =  0 ; display;    
clk =  1 ; display;    
clk =  0 ; display;    
clk =  0 ; display;    
clk =  0 ; display;    
clk =  0 ; display;    
clk =  1 ; display;    
clk =  1 ; display;    
clk =  1 ; display;    
clk =  1 ; display;    
clk =  1 ; display;    
clk =  1 ; display;    
clk =  1 ; display;    
clk =  1 ; display;    
clk =  0 ; display;    
clk =  0 ; display;    
clk =  1 ; display;    
clk =  1 ; display;    
clk =  0 ; display;    
clk =  1 ; display;    
clk =  0 ; display;    
clk =  0 ; display;    
clk =  1 ; display;    
clk =  1 ; display;    
clk =  1 ; display;    
clk =  0 ; display;    
clk =  1 ; display;    
clk =  0 ; display;    
clk =  0 ; display;    
clk =  1 ; display;    
clk =  0 ; display;    
clk =  0 ; display;    
clk =  1 ; display;    
clk =  1 ; display;    
clk =  1 ; display;    
clk =  1 ; display;    
clk =  1 ; display;    
clk =  0 ; display;    
clk =  1 ; display;    
clk =  1 ; display;    
clk =  1 ; display;    
clk =  0 ; display;    
clk =  0 ; display;    
clk =  0 ; display;    
clk =  0 ; display;    
clk =  0 ; display;    
clk =  0 ; display;    
clk =  0 ; display;    
clk =  1 ; display;    
clk =  1 ; display;    
clk =  0 ; display;    
clk =  1 ; display;    
clk =  1 ; display;    
clk =  1 ; display;    
clk =  1 ; display;    
clk =  1 ; display;    
clk =  0 ; display;    
clk =  0 ; display;    
clk =  1 ; display;    
clk =  1 ; display;    
clk =  1 ; display;    
clk =  1 ; display;    
clk =  1 ; display;    
clk =  0 ; display;    
clk =  0 ; display;    
clk =  1 ; display;    
clk =  0 ; display;    
clk =  0 ; display;    
clk =  0 ; display;    
clk =  1 ; display;    
clk =  1 ; display;    
clk =  0 ; display;    
clk =  1 ; display;    
clk =  0 ; display;    
clk =  0 ; display;    
clk =  1 ; display;    
clk =  1 ; display;    
clk =  1 ; display;    
clk =  1 ; display;    
clk =  0 ; display;    
clk =  0 ; display;    
clk =  1 ; display;    
clk =  1 ; display;    
clk =  1 ; display;    
clk =  0 ; display;    
clk =  0 ; display;    
clk =  0 ; display;    
clk =  0 ; display;    
clk =  0 ; display;    
clk =  1 ; display;    
clk =  1 ; display;    
clk =  1 ; display;    
clk =  0 ; display;    
clk =  0 ; display;    
clk =  1 ; display;    
clk =  0 ; display;    
clk =  0 ; display;    
clk =  1 ; display;    
clk =  1 ; display;    
clk =  1 ; display;    
clk =  1 ; display;    
clk =  0 ; display;    
clk =  1 ; display;    
clk =  1 ; display;    
clk =  0 ; display;    
clk =  1 ; display;    
clk =  0 ; display;    
clk =  1 ; display;    
clk =  0 ; display;    
clk =  0 ; display;    
clk =  1 ; display;    
clk =  1 ; display;    
clk =  0 ; display;    
clk =  1 ; display;    
clk =  1 ; display;    
clk =  0 ; display;    
clk =  1 ; display;    
clk =  0 ; display;    
clk =  0 ; display;    
clk =  0 ; display;    
clk =  1 ; display;    
clk =  0 ; display;    
clk =  1 ; display;    
clk =  1 ; display;    
clk =  0 ; display;    
clk =  0 ; display;    
clk =  1 ; display;    
clk =  0 ; display;    
clk =  1 ; display;    
clk =  0 ; display;    
clk =  1 ; display;    
clk =  1 ; display;    
clk =  1 ; display;    
clk =  1 ; display;    
clk =  1 ; display;    
clk =  1 ; display;    
clk =  1 ; display;    
clk =  0 ; display;    
clk =  1 ; display;    
clk =  1 ; display;    
clk =  1 ; display;    
clk =  0 ; display;    
clk =  0 ; display;    
clk =  1 ; display;    
clk =  0 ; display;    
clk =  1 ; display;    
clk =  1 ; display;    
clk =  1 ; display;    
clk =  1 ; display;    
clk =  0 ; display;    
clk =  1 ; display;    
clk =  1 ; display;    
clk =  1 ; display;    
clk =  1 ; display;    
clk =  0 ; display;    
clk =  1 ; display;    
clk =  1 ; display;    
clk =  1 ; display;    
clk =  0 ; display;    
clk =  0 ; display;    
clk =  1 ; display;    
clk =  0 ; display;    
clk =  1 ; display;    
clk =  1 ; display;    
clk =  1 ; display;    
clk =  1 ; display;    
clk =  0 ; display;    
clk =  1 ; display;    
clk =  1 ; display;    
clk =  1 ; display;    
clk =  1 ; display;    
clk =  1 ; display;    
clk =  0 ; display;    
clk =  1 ; display;    
clk =  1 ; display;    
clk =  0 ; display;    
clk =  1 ; display;    
clk =  1 ; display;    
clk =  1 ; display;    
clk =  1 ; display;    
clk =  0 ; display;    
clk =  1 ; display; 
   end

  task display;
    #1 $display("clk:%0h, t:%0h, tt:%0h, ttt:%0h, tttt:%0h, ttttt:%0h, m:%0h",
      clk,t, tt, ttt,tttt,ttttt,m);
  endtask

endmodule

fiveclocks.vcd
$date
	Sat Apr 18 19:07:30 2015
$end
$version
	Icarus Verilog
$end
$timescale
	100ps
$end
$scope module five_clocks_tb $end
$var wire 1 ! m $end
$var wire 1 " t $end
$var wire 1 # tt $end
$var wire 1 $ ttt $end
$var wire 1 % tttt $end
$var wire 1 & ttttt $end
$var reg 1 ' b $end
$var reg 1 ( clk $end
$var reg 1 ) reset $end
$scope module FC $end
$var wire 1 * b $end
$var wire 1 + clk $end
$var wire 1 ! m $end
$var wire 1 , reset $end
$var wire 1 " t $end
$var wire 1 # tt $end
$var wire 1 $ ttt $end
$var wire 1 % tttt $end
$var wire 1 & ttttt $end
$var reg 1 - memory $end
$var reg 1 . the $end
$var reg 1 / thethe $end
$var reg 1 0 thethethe $end
$var reg 1 1 thethethethe $end
$var reg 1 2 thethethethethe $end
$upscope $end
$scope task display $end
$upscope $end
$upscope $end
$enddefinitions $end
#0
$dumpvars
x2
x1
x0
x/
x.
x-
1,
0+
0*
1)
0(
0'
x&
x%
x$
x#
x"
x!
$end
#10
0-
0!
02
0&
01
0%
00
0$
0/
0#
1.
1"
1(
1+
#20
0(
0+
#30
1(
1+
#40
0)
0,
#70
0(
0+
#80
0.
0"
1(
1+
#100
0(
0+
#130
12
1&
11
1%
10
1$
1/
1#
1.
1"
1(
1+
#160
0(
0+
#170
0.
0"
1(
1+
#200
0(
0+
#210
0/
0#
1.
1"
1(
1+
#260
0(
0+
#280
0.
0"
1(
1+
#310
0(
0+
#350
00
0$
1/
1#
1.
1"
1(
1+
#360
0(
0+
#390
0.
0"
1(
1+
#400
0(
0+
#420
0/
0#
1.
1"
1(
1+
#440
0(
0+
#470
0.
0"
1(
1+
#500
0(
0+
#510
01
0%
10
1$
1/
1#
1.
1"
1(
1+
#520
0(
0+
#530
0.
0"
1(
1+
#540
0(
0+
#550
0/
0#
1.
1"
1(
1+
#560
0(
0+
#590
0.
0"
1(
1+
#610
0(
0+
#620
00
0$
1/
1#
1.
1"
1(
1+
#630
0(
0+
#650
0.
0"
1(
1+
#670
0(
0+
#680
0/
0#
1.
1"
1(
1+
#690
0(
0+
#700
0.
0"
1(
1+
#710
0(
0+
#740
02
0&
11
1%
10
1$
1/
1#
1.
1"
1(
1+
#750
0(
0+
#770
0.
0"
1(
1+
#780
0(
0+
#820
0/
0#
1.
1"
1(
1+
#830
0(
0+
#860
0.
0"
1(
1+
#870
0(
0+
#880
00
0$
1/
1#
1.
1"
1(
1+
#890
0(
0+
#920
0.
0"
1(
1+
#950
0(
0+
#960
0/
0#
1.
1"
1(
1+
#980
0(
0+
#1000
0.
0"
1(
1+
#1010
0(
0+
#1030
01
0%
10
1$
1/
1#
1.
1"
1(
1+
#1070
0(
0+
#1080
0.
0"
1(
1+
#1110
0(
0+
#1130
0/
0#
1.
1"
1(
1+
#1160
0(
0+
#1180
0.
0"
1(
1+
#1190
0(
0+
#1200
00
0$
1/
1#
1.
1"
1(
1+
#1210
0(
0+
#1220
0.
0"
1(
1+
#1230
0(
0+
#1270
0/
0#
1.
1"
1(
1+
#1280
0(
0+
#1300
0.
0"
1(
1+
#1310
0(
0+
#1330
12
1&
11
1%
10
1$
1/
1#
1.
1"
1(
1+
#1340
0(
0+
#1360
0.
0"
1(
1+
#1380
0(
0+
#1390
0/
0#
1.
1"
1(
1+
#1400
0(
0+
#1410
0.
0"
1(
1+
#1420
0(
0+
#1440
00
0$
1/
1#
1.
1"
1(
1+
#1470
0(
0+
#1480
0.
0"
1(
1+
#1500
0(
0+
#1520
0/
0#
1.
1"
1(
1+
#1530
0(
0+
#1550
0.
0"
1(
1+
#1570
0(
0+
#1580
01
0%
10
1$
1/
1#
1.
1"
1(
1+
#1630
0(
0+
#1640
0.
0"
1(
1+
#1670
0(
0+
#1680
0/
0#
1.
1"
1(
1+
#1710
0(
0+
#1730
0.
0"
1(
1+
#1760
0(
0+
#1770
00
0$
1/
1#
1.
1"
1(
1+
#1790
0(
0+
#1810
0.
0"
1(
1+
#1820
0(
0+
#1830
0/
0#
1.
1"
1(
1+
#1880
0(
0+
#1920
0.
0"
1(
1+
#1930
0(
0+
#1940
02
0&
11
1%
10
1$
1/
1#
1.
1"
1(
1+
#1950
0(
0+
#1970
0.
0"
1(
1+
#2050
0(
0+
#2090
0/
0#
1.
1"
1(
1+
#2110
0(
0+
#2120
0.
0"
1(
1+
#2140
0(
0+
#2150
00
0$
1/
1#
1.
1"
1(
1+
#2180
0(
0+
#2190
0.
0"
1(
1+
#2200
0(
0+
#2240
0/
0#
1.
1"
1(
1+
#2260
0(
0+
#2280
0.
0"
1(
1+
#2300
0(
0+
#2310
01
0%
10
1$
1/
1#
1.
1"
1(
1+
#2340
0(
0+
#2350
0.
0"
1(
1+
#2380
0(
0+
#2390
0/
0#
1.
1"
1(
1+
#2430
0(
0+
#2490
0.
0"
1(
1+
#2520
0(
0+
#2540
00
0$
1/
1#
1.
1"
1(
1+
#2550
0(
0+
#2570
0.
0"
1(
1+
#2580
0(
0+
#2600
0/
0#
1.
1"
1(
1+
#2610
0(
0+
#2630
0.
0"
1(
1+
#2640
0(
0+
#2650
12
1&
11
1%
10
1$
1/
1#
1.
1"
1(
1+
#2680
0(
0+
#2690
0.
0"
1(
1+
#2720
0(
0+
#2740
0/
0#
1.
1"
1(
1+
#2770
0(
0+
#2780
0.
0"
1(
1+
#2790
0(
0+
#2840
00
0$
1/
1#
1.
1"
1(
1+
#2860
0(
0+
#2880
0.
0"
1(
1+
#2890
0(
0+
#2900
0/
0#
1.
1"
1(
1+
#2950
0(
0+
#2960
0.
0"
1(
1+
#2980
0(
0+
#2990
01
0%
10
1$
1/
1#
1.
1"
1(
1+
#3040
0(
0+
#3090
0.
0"
1(
1+
#3110
0(
0+
#3170
0/
0#
1.
1"
1(
1+
#3180
0(
0+
#3190
0.
0"
1(
1+
#3250
0(
0+
#3260
00
0$
1/
1#
1.
1"
1(
1+
#3270
0(
0+
#3280
0.
0"
1(
1+
#3290
0(
0+
#3320
0/
0#
1.
1"
1(
1+
#3340
0(
0+
#3350
0.
0"
1(
1+
#3360
0(
0+
#3390
02
0&
11
1%
10
1$
1/
1#
1.
1"
1(
1+
#3440
0(
0+
#3450
0.
0"
1(
1+
#3470
0(
0+
#3480
0/
0#
1.
1"
1(
1+
#3490
0(
0+
#3510
0.
0"
1(
1+
#3520
0(
0+
#3530
00
0$
1/
1#
1.
1"
1(
1+
#3540
0(
0+
#3560
0.
0"
1(
1+
#3570
0(
0+
#3580
0/
0#
1.
1"
1(
1+
#3600
0(
0+
#3620
0.
0"
1(
1+
#3630
0(
0+
#3660
01
0%
10
1$
1/
1#
1.
1"
1(
1+
#3670
0(
0+
#3690
0.
0"
1(
1+
#3750
0(
0+
#3780
0/
0#
1.
1"
1(
1+
#3790
0(
0+
#3820
0.
0"
1(
1+
#3850
0(
0+
#3870
00
0$
1/
1#
1.
1"
1(
1+
#3900
0(
0+
#3910
0.
0"
1(
1+
#3920
0(
0+
#3930
0/
0#
1.
1"
1(
1+
#3940
0(
0+
#3980
0.
0"
1(
1+
#4060
0(
0+
#4080
12
1&
11
1%
10
1$
1/
1#
1.
1"
1(
1+
#4100
0(
0+
#4110
0.
0"
1(
1+
#4120
0(
0+
#4140
0/
0#
1.
1"
1(
1+
#4170
0(
0+
#4180
0.
0"
1(
1+
#4190
0(
0+
#4210
00
0$
1/
1#
1.
1"
1(
1+
#4220
0(
0+
#4240
0.
0"
1(
1+
#4290
0(
0+
#4300
0/
0#
1.
1"
1(
1+
#4330
0(
0+
#4400
0.
0"
1(
1+
#4420
0(
0+
#4430
01
0%
10
1$
1/
1#
1.
1"
1(
1+
#4480
0(
0+
#4500
0.
0"
1(
1+
#4550
0(
0+
#4570
0/
0#
1.
1"
1(
1+
#4580
0(
0+
#4610
0.
0"
1(
1+
#4630
0(
0+
#4640
00
0$
1/
1#
1.
1"
1(
1+
#4650
0(
0+
#4670
0.
0"
1(
1+
#4710
0(
0+
#4730
0/
0#
1.
1"
1(
1+
#4760
0(
0+
#4810
0.
0"
1(
1+
#4840
0(
0+
#4860
02
0&
11
1%
10
1$
1/
1#
1.
1"
1(
1+
#4870
0(
0+
#4890
0.
0"
1(
1+
#4930
0(
0+
#4940
0/
0#
1.
1"
1(
1+
#4960
0(
0+
#4970
0.
0"
1(
1+
#4980
0(
0+
#4990
00
0$
1/
1#
1.
1"
1(
1+
#5000
0(
0+
#5020
0.
0"
1(
1+
#5040
0(
0+
#5050
0/
0#
1.
1"
1(
1+
#5070
0(
0+
#5080
0.
0"
1(
1+
#5090
0(
0+
#5120
01
0%
10
1$
1/
1#
1.
1"
1(
1+
#5130
0(
0+
#5140
0.
0"
1(
1+
#5160
0(
0+
#5180
0/
0#
1.
1"
1(
1+
#5190
0(
0+
#5200
0.
0"
1(
1+
#5210
0(
0+
#5220
00
0$
1/
1#
1.
1"
1(
1+
#5290
0(
0+
#5300
0.
0"
1(
1+
#5330
0(
0+
#5350
0/
0#
1.
1"
1(
1+
#5360
0(
0+
#5370
0.
0"
1(
1+
#5410
0(
0+
#5420
12
1&
11
1%
10
1$
1/
1#
1.
1"
1(
1+
#5460
0(
0+
#5470
0.
0"
1(
1+
#5500
0(
0+
#5520
0/
0#
1.
1"
1(
1+
#5530
0(
0+
#5540
0.
0"
1(
1+
#5580
0(
0+
#5590
00
0$
1/
1#
1.
1"
1(
1+
#5640
0(
0+
#5650
0.
0"
1(
1+
#5670
0(
0+
#5680
0/
0#
1.
1"
1(
1+
#5720
0(
0+
#5730
0.
0"
1(
1+
